rtl/data_mem.sv
module data_mem (
    input logic clk,
    input logic mem_write,
    input logic [31:0] addr,
    input logic [31:0] write_data,
    output logic [31:0] read_data
);

    // Create a data RAM array storage block (64 memory slots deep)
    logic [31:0] ram_array [0:63];

    // PRE-LOAD UNSORTED TEST ARRAY INTO RAM
    initial begin
        ram_array[0] = 32'd6;   // RAM[0] (Addr 0x00): Array length N = 6
        ram_array[1] = 32'd42;  // RAM[1] (Addr 0x04): Array[0]
        ram_array[2] = 32'd12;  // RAM[2] (Addr 0x08): Array[1]
        ram_array[3] = 32'd88;  // RAM[3] (Addr 0x0C): Array[2]
        ram_array[4] = 32'd3;   // RAM[4] (Addr 0x10): Array[3]
        ram_array[5] = 32'd27;  // RAM[5] (Addr 0x14): Array[4]
        ram_array[6] = 32'd10;  // RAM[6] (Addr 0x18): Array[5]
    end

    always_ff @(posedge clk) begin
        if (mem_write) begin
            ram_array[addr[31:2]] <= write_data;
        end
    end

    // Asynchronous Combinational Reads: RAM constantly exposes the target data
    assign read_data = ram_array[addr[31:2]];
    

endmodule

rtl/alu.sv
module alu (
    input  logic [31:0] a,          // Operand A (from Register File rs1)
    input  logic [31:0] b,          // Operand B (from Register File rs2 or Immediate)
    input  logic [3:0]  alu_ctrl,   // 4-bit control menu from the Control Unit
    output logic [31:0] result,     // Calculated output
    output logic        zero        // High (1) if result is exactly 0
);

    // Clean compile fix: Extract the lower 5 bits of 'b' into an isolated wire
    // to stop the simulator from crying about constant-select processes.
    logic [4:0] shift_amt;
    assign shift_amt = b[4:0];

    // Combinational multiplexer logic block
    always_comb begin
        case (alu_ctrl)
            // --- ARITHMETIC ---
            4'b0010: result = a + b;                        // ADD (Used by add, addi, lw, sw)
            4'b0110: result = a - b;                        // SUB (Used by sub, beq)
            
            // --- LOGICALS ---
            4'b0000: result = a & b;                        // Bitwise AND (and, andi)
            4'b0001: result = a | b;                        // Bitwise OR (or, ori)
            4'b0011: result = a ^ b;                        // Bitwise XOR (xor, xori)
            
            // --- SHIFTS ---
            4'b0100: result = a << shift_amt;               // SLL (Shift Left Logical / sll, slli)
            4'b0101: result = a >> shift_amt;               // SRL (Shift Right Logical / srl, srli)
            
            // Note: We cast 'a' to signed here so the >>> operator replicates the sign bit (bit 31)
            // instead of filling vacated spots with zeros.
            4'b1101: result = $unsigned(signed'(a) >>> shift_amt); // SRA (Shift Right Arithmetic / sra, srai)

            // --- DEFAULT FALLBACK ---
            default: result = 32'h0000_0000;                // Prevents accidental latch synthesis
        endcase
    end

    // Continuous assignment for the branch evaluation flag
    assign zero = (result == 32'h0000_0000);

endmodule

rtl/imm_gen.sv
module imm_gen (
    input  logic [31:0] inst,       // Raw 32-bit instruction from memory
    output logic [31:0] imm_ext     // 32-bit sign-extended constant output
);

    always_comb begin
        case (inst[6:0]) // Read the 7-bit opcode to see how the bits are arranged
            
            // --- I-TYPE (addi, lw) ---
            // Immediates are cleanly packed in bits [31:20]
            7'b0010011, // addi
            7'b0000011: begin // lw
                imm_ext = { {20{inst[31]}}, inst[31:20] };
            end

            // --- S-TYPE (sw) ---
            // Immediates are split into [31:25] and [11:7]
            7'b0100011: begin
                imm_ext = { {20{inst[31]}}, inst[31:25], inst[11:7] };
            end

            // --- B-TYPE (beq) ---
            // Scrambled layout: inst[31]=sign, inst[7]=bit 11, inst[30:25]=bits 10:5, inst[11:8]=bits 4:1
            // Note: Conditional branches always jump by multiples of 2, so bit 0 is implicitly 1'b0!
            7'b1100011: begin
                imm_ext = { {19{inst[31]}}, inst[31], inst[7], inst[30:25], inst[11:8], 1'b0 };
            end

            // --- J-TYPE (jal) ---
            7'b1101111: begin
                // Slices bits: Sign, imm[19:12], imm[11], imm[10:1], and sets hardwired 0 bit alignment
                imm_ext = { {12{inst[31]}}, inst[19:12], inst[20], inst[30:21], 1'b0 };
            end

            // --- DEFAULT FALLBACK ---
            default: begin
                imm_ext = 32'h0000_0000; // Safe zero fallback to prevent latches
            end
        endcase
    end

endmodule

rtl/register_file.sv
module register_file (
  input  logic        clk,         // System Clock
  input  logic        rst_n,       // Active-Low Reset
  input  logic        reg_write,   // Write Enable control bit (1 = Write data, 0 = Freeze)
  input  logic [4:0]  raddr1,         // 5-bit Source Register 1 Address Pointer
  input  logic [4:0]  raddr2,         // 5-bit Source Register 2 Address Pointer
  input  logic [4:0]  waddr,          // 5-bit Destination Register Address Pointer
  input  logic [31:0] write_data,  // 32-bit data vector waiting to be stored
  output logic [31:0] read_data1,  // 32-bit data currently inside raddr1
  output logic [31:0] read_data2   // 32-bit data currently inside raddr2
);

  // Unpacked Array: 32 rows, each 32-bits wide
  logic [31:0] rf [0:31];

  // --- READ PORTS (Pure Combinational Logic) ---
  assign read_data1 = (raddr1 == 5'b00000) ? 32'b0 : rf[raddr1];
  assign read_data2 = (raddr2 == 5'b00000) ? 32'b0 : rf[raddr2];


  // --- WRITE PORT (Clocked Sequential Logic) ---
  always_ff @(posedge clk or negedge rst_n) begin
    if (!rst_n) begin
      for (int i = 1; i < 32; i++) begin
        rf[i] <= 32'h0000_0000;
      end
    end else begin     
      if (write_data && waddr != 5'b0) begin 
        rf[waddr] <= write_data;
      end
    end
  end

endmodule

rtl/control_unit.sv
module control_unit (
    input  logic [6:0] opcode,      // instruction[6:0]
    input  logic [2:0] funct3,      // instruction[14:12]
    input  logic       funct7_b5,   // instruction[30] (Differentiates ADD/SUB, SRL/SRA)
    
    // Control Routing Signals
    output logic       reg_write,   // 1 = Write to Register File
    output logic       alu_src,     // 0 = Use Reg Data 2, 1 = Use Immediate
    output logic       mem_write,   // 1 = Write to Data Memory (sw)
    output logic       mem_to_reg,  // 0 = ALU result to Reg, 1 = Mem data to Reg
    output logic       branch,      // 1 = This is a branch instruction (beq)
    
    // ALU Specific Output
    output logic [3:0] alu_ctrl     // 4-bit code sent directly to your ALU
);

    // Internal tracking wire to pass info from Main Decoder to ALU Decoder
    logic [1:0] alu_op;

    // ==========================================
    // 1. MAIN DECODER BLOCK
    // ==========================================
    always_comb begin
        // Set defaults to prevent dangerous hardware latches
        reg_write  = 1'b0;
        alu_src    = 1'b0;
        mem_write  = 1'b0;
        mem_to_reg = 1'b0;
        branch     = 1'b0;
        alu_op     = 2'b00;

        case (opcode)
            // --- R-TYPE Instructions (add, sub, xor, etc.) ---
            7'b0110011: begin
                reg_write  = 1'b1;
                alu_src    = 1'b0; // Use register data 2
                mem_write  = 1'b0;
                mem_to_reg = 1'b0; // Take result from ALU
                branch     = 1'b0;
                alu_op     = 2'b10; // "Look at funct3/funct7 to decide math"
            end

            // --- I-TYPE Load Instructions (lw) ---
            7'b0000011: begin
                reg_write = 1'b0;
                alu_src = 1'b1;
                mem_write = 1'b0;
                mem_to_reg = 1'b1;
                branch = 1'b0;
                alu_op = 2'b00;
                // Think: Does a load write to registers? Does it use an immediate?
            end

            // --- S-TYPE Store Instructions (sw) ---
            7'b0100011: begin
                reg_write = 1'b0;
                alu_src = 1'b1;
                mem_write = 1'b1;
                mem_to_reg = 1'b0;
                branch = 1'b0;
                alu_op = 2'b00;
                // Think: Does a store write to registers? Does it write to memory?
            end

            // --- B-TYPE Branch Instructions (beq) ---
            7'b1100011: begin
                reg_write = 1'b0;
                alu_src = 1'b0;
                mem_write = 1'b0;
                mem_to_reg = 1'b0;
                branch = 1'b1;
                alu_op = 2'b01;
                // Think: Does it perform a subtraction to check for equality?
                alu_op     = 2'b01; // "Force a subtraction"
            end

            default: begin
                // Keep defaults if opcode is unknown
            end
        endcase
    end


    // ==========================================
    // 2. ALU DECODER BLOCK
    // ==========================================
    always_comb begin
        // Default to a safe fallback operation (e.g., ADD)
        alu_ctrl = 4'b0010; 

        case (alu_op)
            2'b00: alu_ctrl = 4'b0010; // Force ADD (Used for address calculations in lw/sw)
            
            2'b01: alu_ctrl = 4'b0110; // Force SUB (Used for branches like beq)
            
            2'b10: begin // R-Type Instructions: Must closely inspect funct3 and funct7
                case (funct3)
                    3'b000: begin
                        if (funct7_b5) 
                            alu_ctrl = 4'b0110; // SUB
                        else           
                            alu_ctrl = 4'b0010; // ADD
                    end
                    
                    3'b100: alu_ctrl = 4'b0011; // XOR
                    3'b110: alu_ctrl = 4'b0001; // OR
                    3'b111: alu_ctrl = 4'b0000; // AND
                    
                    // --- SHIFTS ---
                    3'b001: alu_ctrl = 4'b0100; // SLL (Shift Left Logical)
                    3'b101: begin
                        if (funct7_b5)
                            alu_ctrl = 4'b1101; // SRA (Shift Right Arithmetic)
                        else
                            alu_ctrl = 4'b0101; // SRL (Shift Right Logical)
                    end
                    
                    default: alu_ctrl = 4'b0010;
                endcase
            end
            
            default: alu_ctrl = 4'b0010;
        endcase
    end

endmodule

rtl/instru_mem.sv
module instruction_mem (
    input  logic [31:0] pc_addr,
    output logic [31:0] instruction
);

    // Create an unpacked array to act as storage slots (e.g., 64 words deep)
    logic [31:0] mem_array [0:63];

    // Read the compiled machine code text file automatically at simulation startup
    initial begin
        $readmemh("hex/SelectionSort.hex", mem_array);
    end

    // Word-addressing alignment layout: 
    // Because the PC increments by 4 bytes per instruction, we drop the bottom 
    // two bits (shift right by 2) to align the address with our array indexes.
    assign instruction = mem_array[pc_addr[31:2]];

endmodule

rtl/pc.sv
module program_counter (
  input  logic        clk,       // System Clock
  input  logic        rst_n,     // Active-Low Asynchronous Reset
  input  logic [31:0] pc_next,   // 32-bit target address calculated by the CPU
  output logic [31:0] pc_out     // 32-bit current instruction pointer address
);

  // 'always_ff' creates physical D-Flip-Flop registers
  always_ff @(posedge clk or negedge rst_n) begin
    if (!rst_n) begin
      // Clear pc_out to a 32-bit zero literal.
      pc_out <= 32'b0;
      
    end else begin
      // next address into your memory register.
      pc_out <= pc_next;
    end
  end

endmodule


module pc_adder (
  input logic [31:0] pc_curr,
  output logic [31:0] pc_next
);
  
  always_comb begin
    pc_next = pc_curr + 32'd4;
  end
  
endmodule

rtl/riscv_core.sv
module riscv_core (
    input logic clk,
    input logic rst_n
);

    // ==========================================
    // 1. INTERNAL WIRE DECLARATIONS (The Copper)
    // ==========================================
    // Program Counter Wires
    logic [31:0] pc_current;
    logic [31:0] pc_next;
    logic [31:0] pc_plus4;

    // Instruction Bus
    logic [31:0] inst;

    // Control Unit Output Signals
    logic       reg_write;
    logic       alu_src;
    logic       mem_write;
    logic       mem_to_reg;
    logic       branch;
    logic [3:0] alu_ctrl;

    // Register File Wires
    logic [31:0] reg_data1;
    logic [31:0] reg_data2;
    logic [31:0] reg_write_data;

    // Immediate Generator Output
    logic [31:0] imm_ext;

    // ALU Wires
    logic [31:0] alu_operand_b; // Output of the Hour 3 Mux
    logic [31:0] alu_result;
    logic        alu_zero;

    // Data Memory Wires
    logic [31:0] mem_read_data;


    // ==========================================
    // 2. MODULE INSTANTIATIONS (The Silicon Blocks)
    // ==========================================

    // --- Program Counter (PC) Register ---
    program_counter u_program_counter (
        .clk(clk),
        .rst_n(rst_n),
        .pc_next(pc_next),
        .pc_out(pc_current)
    );
    // It should update 'pc_current <= pc_next' on clk edge when rst_n is high.


    // --- PC Adder ---
    assign pc_plus4 = pc_current + 32'd4;


    // --- Placeholder: Instruction Memory ---
    instruction_mem u_instruction_mem (
        .pc_addr(pc_current),
        .instruction(inst)
    );
    // Input: pc_current, Output: inst


    // --- Control Unit ---
    control_unit u_control_unit (
        .opcode     (inst[6:0]),
        .funct3     (inst[14:12]),
        .funct7_b5  (inst[30]),
        .reg_write  (reg_write),
        .alu_src    (alu_src),
        .mem_write  (mem_write),
        .mem_to_reg (mem_to_reg),
        .branch     (branch),
        .alu_ctrl   (alu_ctrl)
    );


    // --- Register File ---
    // Assuming a standard port layout: clk, reg_write, rs1, rs2, rd, write_data, read_data1, read_data2
    register_file u_register_file (
        .clk        (clk),
        .rst_n      (rst_n),
        .reg_write  (reg_write),
        .raddr1     (inst[19:15]),      // rs1
        .raddr2     (inst[24:20]),      // rs2 
        .waddr      (inst[11:7]),       // rd
        .write_data      (reg_write_data),   // Comes from the Writeback Mux
        .read_data1     (reg_data1),
        .read_data2     (reg_data2)
    );


    // --- Immediate Generator ---
    imm_gen u_imm_gen (
        .inst       (inst),
        .imm_ext    (imm_ext)
    );


    // --- Arithmetic Logic Unit (ALU) ---
    alu u_alu (
        .a          (reg_data1),
        .b          (alu_operand_b),    // Fed by the ALU source multiplexer
        .alu_ctrl   (alu_ctrl),
        .result     (alu_result),
        .zero       (alu_zero)
    );


    // --- Placeholder: Data Memory (RAM) ---
    data_mem u_data_mem (
        .clk (clk),
        .mem_write (mem_write),
        .addr (alu_result),
        .write_data (reg_data2),
        .read_data (mem_read_data)
    );
    
    // Inputs: clk, alu_result (addr), reg_data2 (write data), mem_write (we)
    // Output: mem_read_data

    // ==========================================
    // 3. DATAPATH STEERING SWITCHES (Multiplexers)
    // ==========================================
    
    // Next PC Mux: If (Branch Instruction AND ALU says inputs equal), jump! Otherwise PC + 4
    assign pc_next = (branch & alu_zero) ? (pc_current + imm_ext) : pc_plus4; //??? eq check with logical unit and not subtract normally?

    // ALU Input Source Mux: 0 = Use Register Data 2, 1 = Use Sign-Extended Immediate
    assign alu_operand_b = alu_src ? imm_ext : reg_data2;

    // Register Writeback Mux: 0 = Save ALU Math, 1 = Save Data Memory Read
    assign reg_write_data = mem_to_reg ? mem_read_data : alu_result;


endmodule

rtl/tb_riscv_core.sv
`timescale 1ns/1ps

module tb_riscv_core;

    // 1. System Signals
    logic clk;
    logic rst_n;

    // 2. Instantiate the Upgraded CPU Core
    riscv_core uut (
        .clk   (clk),
        .rst_n (rst_n)
    );

    // 3. Clock Generator (50MHz Clock -> Toggles every 10ns, 20ns period)
    always begin
        #10 clk = ~clk;
    end

    // 4. Test Control Sequence
    initial begin
        $display("==========================================================================");
        $display("             STARTING RISC-V CORE CLOSED-LOOP VERIFICATION                ");
        $display("==========================================================================");
        
        // Initialize and force Reset
        clk = 0;
        rst_n = 0; 
        
        // Hold reset for 25ns to let clocks align across a edge transition
        #25;
        rst_n = 1; // Release reset, execution begins at PC 0x00000000

        // Run the simulation for 6 full clock cycles (120ns) to step through our program
        #120;

        $display("==========================================================================");
        $display("                       SIMULATION COMPLETE                                ");
        $display("==========================================================================");
        $finish;
    end

    // 5. Advanced Hierarchical Real-Time Monitor
    // NOTE: If your register file array is named something other than 'rf' (like 'registers' or 'mem'),
    // change uut.u_reg_file.rf[...] to match your exact internal array variable name!
    initial begin
        $monitor("Time=%-3t | PC=%h | Inst=%h | ALU_Res=%-3d | RegW=%b | mem_write_src = %-2d | mem_write = %d | x1=%-2d | x2=%-2d | x3=%-2d | RAM[4]=%-2d | RAM[3]=%-3d | arrindex=%-3d", 
                 $time, 
                 uut.pc_current, 
                 uut.inst, 
                 uut.alu_result, 
                 uut.reg_write,
                 uut.reg_write_src,
                 uut.mem_write,
                 uut.u_register_file.rf[1],  // Hierarchical spy: Destination register
                 uut.u_register_file.rf[2],  // Hierarchical spy: Comparison register
                 uut.u_register_file.rf[3],  // Hierarchical spy: Store data register
                 uut.u_data_mem.ram_array[4], // Hierarchical spy: RAM address 4 (word index 1)
                 uut.u_data_mem.ram_array[3],
                 uut.u_data_mem.addr[31:2]
        );
    end

    // 6. Automatically generate VCD Waveform log files for GTKWave
    initial begin
        $dumpfile("cpu_simulation.vcd");
        $dumpvars(0, tb_riscv_core);
    end

endmodule

/*
`timescale 1ns/1ps

module tb_riscv_core;

    // 1. Declare clock and reset signals
    logic clk;
    logic rst_n;

    // 2. Instantiate your top-level CPU Core
    riscv_core uut (
        .clk   (clk),
        .rst_n (rst_n)
    );

    // 3. Clock Generator (100MHz clock: ticks every 5ns)
    always begin
        #5 clk = ~clk;
    end

    // 4. Test Stimulation Sequence
    initial begin
        // Initialize signals
        clk = 0;
        rst_n = 0; // Assert reset active low

        // Wait 20ns, then release reset
        #20 rst_n = 1;

        // Run simulation for a few clock cycles to let electricity settle
        #40;

        // Stop the simulation safely
        $display("--- Simulation Completed Successfully ---");
        $finish;
    end

    // 5. Real-Time Monitor: Print diagnostic variables directly to terminal
    // We spy inside the uut instance using hierarchical paths (uut.variable_name)
    initial begin
        $monitor("Time=%0t | PC=%h | Inst=%h | ALU Ctrl=%b | ALU Result=%d | Reg Write=%b", 
                 $time, uut.pc_current, uut.inst, uut.alu_ctrl, uut.alu_result, uut.reg_write);
    end

    // 6. Optional: Generate Waveform Dumps for GTKWave
    initial begin
        $dumpfile("cpu_simulation.vcd");
        $dumpvars(0, tb_riscv_core);
    end

endmodule
*/

rtl/cpu_simulation.vcd
$date
	Tue Jun 23 14:16:01 2026
$end
$version
	Icarus Verilog
$end
$timescale
	1ps
$end
$scope module tb_riscv_core $end
$var reg 1 ! clk $end
$var reg 1 " rst_n $end
$scope module uut $end
$var wire 1 ! clk $end
$var wire 1 " rst_n $end
$var wire 32 # reg_write_data [31:0] $end
$var wire 1 $ reg_write $end
$var wire 32 % reg_data2 [31:0] $end
$var wire 32 & reg_data1 [31:0] $end
$var wire 32 ' pc_plus4 [31:0] $end
$var wire 32 ( pc_next [31:0] $end
$var wire 32 ) pc_current [31:0] $end
$var wire 1 * mem_write $end
$var wire 1 + mem_to_reg $end
$var wire 32 , mem_read_data [31:0] $end
$var wire 32 - inst [31:0] $end
$var wire 32 . imm_ext [31:0] $end
$var wire 1 / branch $end
$var wire 1 0 alu_zero $end
$var wire 1 1 alu_src $end
$var wire 32 2 alu_result [31:0] $end
$var wire 32 3 alu_operand_b [31:0] $end
$var wire 4 4 alu_ctrl [3:0] $end
$scope module u_alu $end
$var wire 32 5 b [31:0] $end
$var wire 1 0 zero $end
$var wire 5 6 shift_amt [4:0] $end
$var wire 4 7 alu_ctrl [3:0] $end
$var wire 32 8 a [31:0] $end
$var reg 32 9 result [31:0] $end
$upscope $end
$scope module u_control_unit $end
$var wire 3 : funct3 [2:0] $end
$var wire 1 ; funct7_b5 $end
$var wire 7 < opcode [6:0] $end
$var reg 4 = alu_ctrl [3:0] $end
$var reg 2 > alu_op [1:0] $end
$var reg 1 1 alu_src $end
$var reg 1 / branch $end
$var reg 1 + mem_to_reg $end
$var reg 1 * mem_write $end
$var reg 1 $ reg_write $end
$upscope $end
$scope module u_data_mem $end
$var wire 32 ? addr [31:0] $end
$var wire 1 ! clk $end
$var wire 1 * mem_write $end
$var wire 32 @ read_data [31:0] $end
$var wire 32 A write_data [31:0] $end
$upscope $end
$scope module u_imm_gen $end
$var wire 32 B inst [31:0] $end
$var reg 32 C imm_ext [31:0] $end
$upscope $end
$scope module u_instruction_mem $end
$var wire 32 D instruction [31:0] $end
$var wire 32 E pc_addr [31:0] $end
$upscope $end
$scope module u_program_counter $end
$var wire 1 ! clk $end
$var wire 32 F pc_next [31:0] $end
$var wire 1 " rst_n $end
$var reg 32 G pc_out [31:0] $end
$upscope $end
$scope module u_register_file $end
$var wire 1 ! clk $end
$var wire 5 H raddr1 [4:0] $end
$var wire 5 I raddr2 [4:0] $end
$var wire 1 $ reg_write $end
$var wire 1 " rst_n $end
$var wire 5 J waddr [4:0] $end
$var wire 32 K write_data [31:0] $end
$var wire 32 L read_data2 [31:0] $end
$var wire 32 M read_data1 [31:0] $end
$scope begin $ivl_for_loop0 $end
$var integer 32 N i [31:0] $end
$upscope $end
$upscope $end
$upscope $end
$upscope $end
$enddefinitions $end
$comment Show the parameter values. $end
$dumpall
$end
#0
$dumpvars
b100000 N
b0 M
b0 L
b1010 K
b1 J
b1010 I
b0 H
b0 G
b100 F
b0 E
b101000000000000010010011 D
b1010 C
b101000000000000010010011 B
b0 A
bx @
b1010 ?
b0 >
b10 =
b10011 <
0;
b0 :
b1010 9
b0 8
b10 7
b1010 6
b1010 5
b10 4
b1010 3
b1010 2
11
00
0/
b1010 .
b101000000000000010010011 -
bx ,
0+
0*
b0 )
b100 (
b100 '
b0 &
b0 %
1$
b1010 #
0"
0!
$end
#10000
b100000 N
1!
#20000
0!
#25000
1"
#30000
b100 #
b100 K
b100 2
b100 9
b100 ?
b100 6
b100 3
b100 5
b10 J
b100 I
b100 .
b100 C
b10000000000000100010011 -
b10000000000000100010011 B
b10000000000000100010011 D
b1000 (
b1000 F
b1000 '
b100 )
b100 E
b100 G
1!
#40000
0!
#50000
b1110 #
b1110 K
b100 %
b100 A
b100 L
b1110 2
b1110 9
b1110 ?
b100 6
b1010 &
b1010 8
b1010 M
b10 >
01
1$
b100 3
b100 5
b11 J
b10 I
b1 H
b110011 <
b0 .
b0 C
b1000001000000110110011 -
b1000001000000110110011 B
b1000001000000110110011 D
b1100 (
b1100 F
b1100 '
b1000 )
b1000 E
b1000 G
1!
#60000
0!
#70000
b110 #
b110 K
b110 2
b110 9
b110 ?
b110 4
b110 7
b110 =
b100 J
1;
b1000000001000001000001000110011 -
b1000000001000001000001000110011 B
b1000000001000001000001000110011 D
b10000 (
b10000 F
b10000 '
b1100 )
b1100 E
b1100 G
1!
#80000
0!
#90000
b10000 #
b10000 K
b10000 6
b1110 %
b1110 A
b1110 L
b10000 2
b10000 9
b10000 ?
b10000 3
b10000 5
b0 &
b0 8
b0 M
b10 4
b10 7
b10 =
1*
11
b0 >
0$
b10000 J
b11 I
b0 H
0;
b10 :
b100011 <
b10000 .
b10000 C
b1100000010100000100011 -
b1100000010100000100011 B
b1100000010100000100011 D
b10100 (
b10100 F
b10100 '
b10000 )
b10000 E
b10000 G
1!
#100000
0!
#110000
b10000 %
b10000 A
b10000 L
b1110 #
b1110 K
1+
1$
0*
11
b101 J
b10000 I
b11 <
b1000000000010001010000011 -
b1000000000010001010000011 B
b1000000000010001010000011 D
b11000 (
b11000 F
b1110 ,
b1110 @
b11000 '
b10100 )
b10100 E
b10100 G
1!
#120000
0!
#130000
10
bx ,
bx @
b1110 %
b1110 A
b1110 L
b0 #
b0 K
b0 2
b0 9
b0 ?
b1110 6
b1110 &
b1110 8
b1110 M
b110 4
b110 7
b110 =
b1 >
1/
0+
01
0$
b1110 3
b1110 5
b1 J
b101 I
b11 H
1;
b0 :
b1100011 <
b11111111111111111111111111000000 .
b11111111111111111111111111000000 C
b11111100010100011000000011100011 -
b11111100010100011000000011100011 B
b11111100010100011000000011100011 D
b11111111111111111111111111011000 (
b11111111111111111111111111011000 F
b11100 '
b11000 )
b11000 E
b11000 G
1!
