rtl/data_mem.sv
module data_mem (
    input logic clk,
    input logic mem_write,
    input logic [31:0] addr,
    input logic [31:0] write_data,
    output logic [31:0] read_data
);

    // Create a data RAM array storage block (64 memory slots deep)
    logic [31:0] ram_array [0:63];

    // PRE-LOAD UNSORTED TEST ARRAY INTO RAM
    initial begin
        ram_array[0] = 32'd6;   // RAM[0] (Addr 0x00): Array length N = 6
        ram_array[1] = 32'd42;  // RAM[1] (Addr 0x04): Array[0]
        ram_array[2] = 32'd12;  // RAM[2] (Addr 0x08): Array[1]
        ram_array[3] = 32'd88;  // RAM[3] (Addr 0x0C): Array[2]
        ram_array[4] = 32'd3;   // RAM[4] (Addr 0x10): Array[3]
        ram_array[5] = 32'd27;  // RAM[5] (Addr 0x14): Array[4]
        ram_array[6] = 32'd10;  // RAM[6] (Addr 0x18): Array[5]
    end

    always_ff @(posedge clk) begin
        if (mem_write) begin
            ram_array[addr[31:2]] <= write_data;
        end
    end

    // Asynchronous Combinational Reads: RAM constantly exposes the target data
    assign read_data = ram_array[addr[31:2]];
    

endmodule

rtl/alu.sv
module alu (
    input  logic [31:0] a,          // Operand A (from Register File rs1)
    input  logic [31:0] b,          // Operand B (from Register File rs2 or Immediate)
    input  logic [3:0]  alu_ctrl,   // 4-bit control menu from the Control Unit
    output logic [31:0] result,     // Calculated output
    output logic        zero        // High (1) if result is exactly 0
);

    // Clean compile fix: Extract the lower 5 bits of 'b' into an isolated wire
    // to stop the simulator from crying about constant-select processes.
    logic [4:0] shift_amt;
    assign shift_amt = b[4:0];

    // Combinational multiplexer logic block
    always_comb begin
        case (alu_ctrl)
            // --- ARITHMETIC ---
            4'b0010: result = a + b;                        // ADD (Used by add, addi, lw, sw)
            4'b0110: result = a - b;                        // SUB (Used by sub, beq)
            
            // --- LOGICALS ---
            4'b0000: result = a & b;                        // Bitwise AND (and, andi)
            4'b0001: result = a | b;                        // Bitwise OR (or, ori)
            4'b0011: result = a ^ b;                        // Bitwise XOR (xor, xori)
            
            // --- SHIFTS ---
            4'b0100: result = a << shift_amt;               // SLL (Shift Left Logical / sll, slli)
            4'b0101: result = a >> shift_amt;               // SRL (Shift Right Logical / srl, srli)
            
            // Note: We cast 'a' to signed here so the >>> operator replicates the sign bit (bit 31)
            // instead of filling vacated spots with zeros.
            4'b1101: result = $unsigned(signed'(a) >>> shift_amt); // SRA (Shift Right Arithmetic / sra, srai)

            // --- DEFAULT FALLBACK ---
            default: result = 32'h0000_0000;                // Prevents accidental latch synthesis
        endcase
    end

    // Continuous assignment for the branch evaluation flag
    assign zero = (result == 32'h0000_0000);

endmodule

rtl/imm_gen.sv
module imm_gen (
    input  logic [31:0] inst,       // Raw 32-bit instruction from memory
    output logic [31:0] imm_ext     // 32-bit sign-extended constant output
);

    always_comb begin
        case (inst[6:0]) // Read the 7-bit opcode to see how the bits are arranged
            
            // --- I-TYPE (addi, lw) ---
            // Immediates are cleanly packed in bits [31:20]
            7'b0010011, // addi
            7'b0000011: begin // lw
                imm_ext = { {20{inst[31]}}, inst[31:20] };
            end

            // --- S-TYPE (sw) ---
            // Immediates are split into [31:25] and [11:7]
            7'b0100011: begin
                imm_ext = { {20{inst[31]}}, inst[31:25], inst[11:7] };
            end

            // --- B-TYPE (beq) ---
            // Scrambled layout: inst[31]=sign, inst[7]=bit 11, inst[30:25]=bits 10:5, inst[11:8]=bits 4:1
            // Note: Conditional branches always jump by multiples of 2, so bit 0 is implicitly 1'b0!
            7'b1100011: begin
                imm_ext = { {19{inst[31]}}, inst[31], inst[7], inst[30:25], inst[11:8], 1'b0 };
            end

            // --- J-TYPE (jal) ---
            7'b1101111: begin
                // Slices bits: Sign, imm[19:12], imm[11], imm[10:1], and sets hardwired 0 bit alignment
                imm_ext = { {12{inst[31]}}, inst[19:12], inst[20], inst[30:21], 1'b0 };
            end

            // --- DEFAULT FALLBACK ---
            default: begin
                imm_ext = 32'h0000_0000; // Safe zero fallback to prevent latches
            end
        endcase
    end

endmodule

rtl/register_file.sv
module register_file (
  input  logic        clk,         // System Clock
  input  logic        rst_n,       // Active-Low Reset
  input  logic        reg_write,   // Write Enable control bit (1 = Write data, 0 = Freeze)
  input  logic [4:0]  raddr1,         // 5-bit Source Register 1 Address Pointer
  input  logic [4:0]  raddr2,         // 5-bit Source Register 2 Address Pointer
  input  logic [4:0]  waddr,          // 5-bit Destination Register Address Pointer
  input  logic [31:0] write_data,  // 32-bit data vector waiting to be stored
  output logic [31:0] read_data1,  // 32-bit data currently inside raddr1
  output logic [31:0] read_data2   // 32-bit data currently inside raddr2
);

  // Unpacked Array: 32 rows, each 32-bits wide
  logic [31:0] rf [0:31];

  // --- READ PORTS (Pure Combinational Logic) ---
  assign read_data1 = (raddr1 == 5'b00000) ? 32'b0 : rf[raddr1];
  assign read_data2 = (raddr2 == 5'b00000) ? 32'b0 : rf[raddr2];


  // --- WRITE PORT (Clocked Sequential Logic) ---
  always_ff @(posedge clk or negedge rst_n) begin
    if (!rst_n) begin
      for (int i = 1; i < 32; i++) begin
        rf[i] <= 32'h0000_0000;
      end
    end else begin     
      if (write_data && waddr != 5'b0) begin 
        rf[waddr] <= write_data;
      end
    end
  end

endmodule

rtl/control_unit.sv
module control_unit (
    input  logic [6:0] opcode,      // instruction[6:0]
    input  logic [2:0] funct3,      // instruction[14:12]
    input  logic       funct7_b5,   // instruction[30] (Differentiates ADD/SUB, SRL/SRA)
    
    // Control Routing Signals
    output logic       reg_write,   // 1 = Write to Register File
    output logic       alu_src,     // 0 = Use Reg Data 2; 1 = Use Immediate
    output logic       mem_write,   // 1 = Write to Data Memory (sw)
    output logic [1:0]     reg_write_src,  // 00 = ALU Output; 01 = Memory; 10 = PC+4 (jal)
    output logic [1:0]      pc_src,      // 00 = pc+4; 01 = branch; 10 = jal; 11 = jalr (alu)
    
    // ALU Specific Output
    output logic [3:0] alu_ctrl     // 4-bit code sent directly to your ALU
);

    // Internal tracking wire to pass info from Main Decoder to ALU Decoder
    logic [1:0] alu_op;

    // ==========================================
    // 1. MAIN DECODER BLOCK
    // ==========================================
    always_comb begin
        // Set defaults to prevent dangerous hardware latches
        reg_write  = 1'b0;
        alu_src    = 1'b0;
        mem_write  = 1'b0;
        reg_write_src = 2'b00;
        pc_src     = 2'b00;
        alu_op     = 2'b00;

        case (opcode)
            // --- R-TYPE Instructions (add, sub, xor, etc.) ---
            7'b0110011: begin
                reg_write  = 1'b1;
                alu_src    = 1'b0; // Use register data 2
                mem_write  = 1'b0;
                reg_write_src = 2'b00; // Take result from ALU
                pc_src     = 2'b00;
                alu_op     = 2'b10; // "Look at funct3/funct7 to decide math"
            end

            // --- I-TYPE Load Instructions (lw) ---
            7'b0000011: begin
                reg_write = 1'b1;
                alu_src = 1'b1;
                mem_write = 1'b0;
                reg_write_src = 2'b01;
                pc_src = 2'b00;
                alu_op = 2'b00;
                // Think: Does a load write to registers? Does it use an immediate?
            end

            // --- I-TYPE Immediate Math Instructions (addi, andi, ori, xori) ---
            7'b0010011: begin
                reg_write = 1'b1;
                alu_src = 1'b1;
                mem_write = 1'b0;
                reg_write_src = 2'b00;
                pc_src = 2'b00;
                alu_op = 2'b10;
            end

            // --- S-TYPE Store Instructions (sw) ---
            7'b0100011: begin
                reg_write = 1'b0;
                alu_src = 1'b1;
                mem_write = 1'b1;
                reg_write_src = 2'b01;
                pc_src = 2'b00;
                alu_op = 2'b00;
                // Think: Does a store write to registers? Does it write to memory?
            end

            // --- B-TYPE pc_src Instructions (beq) ---
            7'b1100011: begin
                reg_write = 1'b0;
                alu_src = 1'b0;
                mem_write = 1'b0;
                reg_write_src = 2'b00; // don't care
                pc_src = 2'b01; //branch
                // Think: Does it perform a subtraction to check for equality?
                alu_op     = 2'b01; // "Force a subtraction"
            end

            // --- JAL (Jump and Link) Unconditional Jump ---
            7'b1101111: begin
                reg_write     = 1'b1;   // YES: Save return address to rd (usually x1/ra)
                alu_src       = 1'b0;   // Don't care
                mem_write     = 1'b0;   // NO RAM interactions
                reg_write_src = 2'b10;  // CRITICAL: Direct writeback multiplexer to select PC + 4
                pc_src        = 2'b10;  // CRITICAL: Force PC to select the JAL target address calculation
                alu_op        = 2'b00;
            end

            // --- JALR (Jump and Link Register) Dynamic Jump ---
            7'b1100111: begin
                reg_write     = 1'b1;   // YES: Save return address to rd
                alu_src       = 1'b1;   // YES: Use immediate value to offset base address
                mem_write     = 1'b0;   // NO RAM interactions
                reg_write_src = 2'b10;  // CRITICAL: Select PC + 4 for destination register
                pc_src        = 2'b11;  // CRITICAL: Force PC to select the calculated Register offset address
                alu_op        = 2'b00;  // Force ALU to perform addition (rs1 + immediate)
            end

            default: begin
                // Keep defaults if opcode is unknown
            end
        endcase
    end


    // ==========================================
    // 2. ALU DECODER BLOCK
    // ==========================================
    always_comb begin
        // Default to a safe fallback operation (e.g., ADD)
        alu_ctrl = 4'b0010; 

        case (alu_op)
            2'b00: alu_ctrl = 4'b0010; // Force ADD (Used for address calculations in lw/sw)
            
            2'b01: 
                case (funct3)
                    3'b000, 3'b001: alu_ctrl = 4'b0110; // BEQ / BNE (SUB)
                    3'b100, 3'b101: alu_ctrl = 4'b0111; // BLT / BGE (Signed Compare)
                    3'b110, 3'b111: alu_ctrl = 4'b1000; // BLTU / BGEU (Unsigned Compare)
                    default:        alu_ctrl = 4'b0110;
                endcase

            
            2'b10: begin // R-Type Instructions: Must closely inspect funct3 and funct7
                case (funct3)
                    3'b000: begin
                        if (funct7_b5) 
                            alu_ctrl = 4'b0110; // SUB
                        else           
                            alu_ctrl = 4'b0010; // ADD
                    end
                    
                    3'b100: alu_ctrl = 4'b0011; // XOR
                    3'b110: alu_ctrl = 4'b0001; // OR
                    3'b111: alu_ctrl = 4'b0000; // AND
                    
                    // --- SHIFTS ---
                    3'b001: alu_ctrl = 4'b0100; // SLL (Shift Left Logical)
                    3'b101: begin
                        if (funct7_b5)
                            alu_ctrl = 4'b1101; // SRA (Shift Right Arithmetic)
                        else
                            alu_ctrl = 4'b0101; // SRL (Shift Right Logical)
                    end
                    
                    default: alu_ctrl = 4'b0010;
                endcase
            end
            
            default: alu_ctrl = 4'b0010;
        endcase
    end

endmodule

rtl/instru_mem.sv
module instruction_mem (
    input  logic [31:0] pc_addr,
    output logic [31:0] instruction
);

    // Create an unpacked array to act as storage slots (e.g., 64 words deep)
    logic [31:0] mem_array [0:63];

    // Read the compiled machine code text file automatically at simulation startup
    initial begin
        $readmemh("hex/SelectionSort.hex", mem_array);
    end

    // Word-addressing alignment layout: 
    // Because the PC increments by 4 bytes per instruction, we drop the bottom 
    // two bits (shift right by 2) to align the address with our array indexes.
    assign instruction = mem_array[pc_addr[31:2]];

endmodule

rtl/pc.sv
module program_counter (
  input  logic        clk,       // System Clock
  input  logic        rst_n,     // Active-Low Asynchronous Reset
  input  logic [31:0] pc_next,   // 32-bit target address calculated by the CPU
  output logic [31:0] pc_out     // 32-bit current instruction pointer address
);

  // 'always_ff' creates physical D-Flip-Flop registers
  always_ff @(posedge clk or negedge rst_n) begin
    if (!rst_n) begin
      // Clear pc_out to a 32-bit zero literal.
      pc_out <= 32'b0;
      
    end else begin
      // next address into your memory register.
      pc_out <= pc_next;
    end
  end

endmodule


module pc_adder (
  input logic [31:0] pc_curr,
  output logic [31:0] pc_next
);
  
  always_comb begin
    pc_next = pc_curr + 32'd4;
  end
  
endmodule

rtl/riscv_core.sv
module riscv_core (
    input logic clk,
    input logic rst_n
);

    // ==========================================
    // 1. INTERNAL WIRE DECLARATIONS (The Copper)
    // ==========================================
    // Program Counter Wires
    logic [31:0] pc_current;
    logic [31:0] pc_next;
    logic [31:0] pc_plus4;

    // Instruction Bus
    logic [31:0] inst;

    // Control Unit Output Signals
    logic       reg_write;
    logic       alu_src;
    logic       mem_write;
    logic    [1:0]   reg_write_src;
    logic    [1:0]   pc_src;
    logic [3:0] alu_ctrl;

    // Register File Wires
    logic [31:0] reg_data1;
    logic [31:0] reg_data2;
    logic [31:0] reg_write_data;

    // Immediate Generator Output
    logic [31:0] imm_ext;

    // ALU Wires
    logic [31:0] alu_operand_b; // Output of the Hour 3 Mux
    logic [31:0] alu_result;
    logic        alu_zero;

    // Data Memory Wires
    logic [31:0] mem_read_data;


    // ==========================================
    // 2. MODULE INSTANTIATIONS (The Silicon Blocks)
    // ==========================================

    // --- Program Counter (PC) Register ---
    program_counter u_program_counter (
        .clk(clk),
        .rst_n(rst_n),
        .pc_next(pc_next),
        .pc_out(pc_current)
    );


    // --- PC Adder ---
    assign pc_plus4 = pc_current + 32'd4;


    // --- Placeholder: Instruction Memory ---
    instruction_mem u_instruction_mem (
        .pc_addr(pc_current),
        .instruction(inst)
    );
    // Input: pc_current, Output: inst


    // --- Control Unit ---
    control_unit u_control_unit (
        .opcode     (inst[6:0]),
        .funct3     (inst[14:12]),
        .funct7_b5  (inst[30]),
        .reg_write  (reg_write),
        .alu_src    (alu_src),
        .mem_write  (mem_write),
        .reg_write_src (reg_write_src),
        .pc_src     (pc_src),
        .alu_ctrl   (alu_ctrl)
    );


    // --- Register File ---
    // Assuming a standard port layout: clk, reg_write, rs1, rs2, rd, write_data, read_data1, read_data2
    register_file u_register_file (
        .clk        (clk),
        .rst_n      (rst_n),
        .reg_write  (reg_write),
        .raddr1     (inst[19:15]),      // rs1
        .raddr2     (inst[24:20]),      // rs2 
        .waddr      (inst[11:7]),       // rd
        .write_data      (reg_write_data),   // Comes from the Writeback Mux
        .read_data1     (reg_data1),
        .read_data2     (reg_data2)
    );


    // --- Immediate Generator ---
    imm_gen u_imm_gen (
        .inst       (inst),
        .imm_ext    (imm_ext)
    );


    // --- Arithmetic Logic Unit (ALU) ---
    alu u_alu (
        .a          (reg_data1),
        .b          (alu_operand_b),    // Fed by the ALU source multiplexer
        .alu_ctrl   (alu_ctrl),
        .result     (alu_result),
        .zero       (alu_zero)
    );


    // --- Placeholder: Data Memory (RAM) ---
    data_mem u_data_mem (
        .clk (clk),
        .mem_write (mem_write),
        .addr (alu_result),
        .write_data (reg_data2),
        .read_data (mem_read_data)
    );
    
    // Inputs: clk, alu_result (addr), reg_data2 (write data), mem_write (we)
    // Output: mem_read_data

    // ==========================================
    // 3. DATAPATH STEERING SWITCHES (Multiplexers)
    // ==========================================
    
    // Compute your distinct path targets
    logic [31:0] pc_target;

    assign pc_target = pc_current + imm_ext; // Relative offset target from immediate block

    // 4-Way PC Generation Control Multiplexer
    always_comb begin
        case (pc_src)
            2'b00:   pc_next = pc_plus4; // Standard sequential step
            
            2'b01:   begin // Branching Check Evaluation
                if (alu_zero) pc_next = pc_target;
                else                    pc_next = pc_plus4;
            end
            
            2'b10:   pc_next = pc_target;  // JAL immediate jump wire
            2'b11:   pc_next = alu_result & 32'hFFFF_FFFE;
            default: pc_next = pc_plus4;
        endcase
    end

    // ALU Input Source Mux: 0 = Use Register Data 2, 1 = Use Sign-Extended Immediate
    assign alu_operand_b = alu_src ? imm_ext : reg_data2;

    // Register Writeback Mux: 
    always_comb begin
        case (reg_write_src)
            2'b00: reg_write_data = alu_result;

            2'b01: reg_write_data = mem_read_data;

            2'b10: reg_write_data = pc_plus4;

            default: reg_write_data = alu_result;
        endcase
    end


endmodule

rtl/tb_riscv_core.sv
`timescale 1ns/1ps

module tb_riscv_core;

    // 1. System Signals
    logic clk;
    logic rst_n;

    // 2. Instantiate the Upgraded CPU Core
    riscv_core uut (
        .clk   (clk),
        .rst_n (rst_n)
    );

    // 3. Clock Generator (50MHz Clock -> Toggles every 10ns, 20ns period)
    always begin
        #10 clk = ~clk;
    end

    // 4. Test Control Sequence
    initial begin
        $display("==========================================================================");
        $display("             STARTING RISC-V CORE CLOSED-LOOP VERIFICATION                ");
        $display("==========================================================================");
        
        // Initialize and force Reset
        clk = 0;
        rst_n = 0; 
        
        // Hold reset for 25ns to let clocks align across a edge transition
        #25;
        rst_n = 1; // Release reset, execution begins at PC 0x00000000

        // Run the simulation for 6 full clock cycles (120ns) to step through our program
        #120;

        $display("==========================================================================");
        $display("                       SIMULATION COMPLETE                                ");
        $display("==========================================================================");
        $finish;
    end

    // 5. Advanced Hierarchical Real-Time Monitor
    // NOTE: If your register file array is named something other than 'rf' (like 'registers' or 'mem'),
    // change uut.u_reg_file.rf[...] to match your exact internal array variable name!
    initial begin
        $monitor("Time=%-3t | PC=%h | Inst=%h | ALU_Res=%-3d | RegW=%b | mem_write_src = %-2d | mem_write = %d | x1=%-2d | x2=%-2d | x3=%-2d | RAM[4]=%-2d | RAM[3]=%-3d | arrindex=%-3d", 
                 $time, 
                 uut.pc_current, 
                 uut.inst, 
                 uut.alu_result, 
                 uut.reg_write,
                 uut.reg_write_src,
                 uut.mem_write,
                 uut.u_register_file.rf[1],  // Hierarchical spy: Destination register
                 uut.u_register_file.rf[2],  // Hierarchical spy: Comparison register
                 uut.u_register_file.rf[3],  // Hierarchical spy: Store data register
                 uut.u_data_mem.ram_array[4], // Hierarchical spy: RAM address 4 (word index 1)
                 uut.u_data_mem.ram_array[3],
                 uut.u_data_mem.addr[31:2]
        );
    end

    // 6. Automatically generate VCD Waveform log files for GTKWave
    initial begin
        $dumpfile("cpu_simulation.vcd");
        $dumpvars(0, tb_riscv_core);
    end

endmodule

/*
`timescale 1ns/1ps

module tb_riscv_core;

    // 1. Declare clock and reset signals
    logic clk;
    logic rst_n;

    // 2. Instantiate your top-level CPU Core
    riscv_core uut (
        .clk   (clk),
        .rst_n (rst_n)
    );

    // 3. Clock Generator (100MHz clock: ticks every 5ns)
    always begin
        #5 clk = ~clk;
    end

    // 4. Test Stimulation Sequence
    initial begin
        // Initialize signals
        clk = 0;
        rst_n = 0; // Assert reset active low

        // Wait 20ns, then release reset
        #20 rst_n = 1;

        // Run simulation for a few clock cycles to let electricity settle
        #40;

        // Stop the simulation safely
        $display("--- Simulation Completed Successfully ---");
        $finish;
    end

    // 5. Real-Time Monitor: Print diagnostic variables directly to terminal
    // We spy inside the uut instance using hierarchical paths (uut.variable_name)
    initial begin
        $monitor("Time=%0t | PC=%h | Inst=%h | ALU Ctrl=%b | ALU Result=%d | Reg Write=%b", 
                 $time, uut.pc_current, uut.inst, uut.alu_ctrl, uut.alu_result, uut.reg_write);
    end

    // 6. Optional: Generate Waveform Dumps for GTKWave
    initial begin
        $dumpfile("cpu_simulation.vcd");
        $dumpvars(0, tb_riscv_core);
    end

endmodule
*/

rtl/cpu_simulation.vcd
$date
	Thu Jul 30 13:10:58 2026
$end
$version
	Icarus Verilog
$end
$timescale
	1ps
$end
$scope module tb_riscv_core $end
$var reg 1 ! clk $end
$var reg 1 " rst_n $end
$scope module uut $end
$var wire 1 ! clk $end
$var wire 1 " rst_n $end
$var wire 2 # reg_write_src [1:0] $end
$var wire 1 $ reg_write $end
$var wire 32 % reg_data2 [31:0] $end
$var wire 32 & reg_data1 [31:0] $end
$var wire 32 ' pc_target [31:0] $end
$var wire 2 ( pc_src [1:0] $end
$var wire 32 ) pc_plus4 [31:0] $end
$var wire 32 * pc_current [31:0] $end
$var wire 1 + mem_write $end
$var wire 32 , mem_read_data [31:0] $end
$var wire 32 - inst [31:0] $end
$var wire 32 . imm_ext [31:0] $end
$var wire 1 / alu_zero $end
$var wire 1 0 alu_src $end
$var wire 32 1 alu_result [31:0] $end
$var wire 32 2 alu_operand_b [31:0] $end
$var wire 4 3 alu_ctrl [3:0] $end
$var reg 32 4 pc_next [31:0] $end
$var reg 32 5 reg_write_data [31:0] $end
$scope module u_alu $end
$var wire 32 6 b [31:0] $end
$var wire 1 / zero $end
$var wire 5 7 shift_amt [4:0] $end
$var wire 4 8 alu_ctrl [3:0] $end
$var wire 32 9 a [31:0] $end
$var reg 32 : result [31:0] $end
$upscope $end
$scope module u_control_unit $end
$var wire 3 ; funct3 [2:0] $end
$var wire 1 < funct7_b5 $end
$var wire 7 = opcode [6:0] $end
$var reg 4 > alu_ctrl [3:0] $end
$var reg 2 ? alu_op [1:0] $end
$var reg 1 0 alu_src $end
$var reg 1 + mem_write $end
$var reg 2 @ pc_src [1:0] $end
$var reg 1 $ reg_write $end
$var reg 2 A reg_write_src [1:0] $end
$upscope $end
$scope module u_data_mem $end
$var wire 32 B addr [31:0] $end
$var wire 1 ! clk $end
$var wire 1 + mem_write $end
$var wire 32 C read_data [31:0] $end
$var wire 32 D write_data [31:0] $end
$upscope $end
$scope module u_imm_gen $end
$var wire 32 E inst [31:0] $end
$var reg 32 F imm_ext [31:0] $end
$upscope $end
$scope module u_instruction_mem $end
$var wire 32 G instruction [31:0] $end
$var wire 32 H pc_addr [31:0] $end
$upscope $end
$scope module u_program_counter $end
$var wire 1 ! clk $end
$var wire 32 I pc_next [31:0] $end
$var wire 1 " rst_n $end
$var reg 32 J pc_out [31:0] $end
$upscope $end
$scope module u_register_file $end
$var wire 1 ! clk $end
$var wire 5 K raddr1 [4:0] $end
$var wire 5 L raddr2 [4:0] $end
$var wire 1 $ reg_write $end
$var wire 1 " rst_n $end
$var wire 5 M waddr [4:0] $end
$var wire 32 N write_data [31:0] $end
$var wire 32 O read_data2 [31:0] $end
$var wire 32 P read_data1 [31:0] $end
$scope begin $ivl_for_loop0 $end
$var integer 32 Q i [31:0] $end
$upscope $end
$upscope $end
$upscope $end
$upscope $end
$enddefinitions $end
$comment Show the parameter values. $end
$dumpall
$end
#0
$dumpvars
b100000 Q
b0 P
b0 O
b1000 N
b1 M
b1000 L
b0 K
b0 J
b100 I
b0 H
b100000000000000010010011 G
b1000 F
b100000000000000010010011 E
b0 D
bx C
b1000 B
b0 A
b0 @
b0 ?
b10 >
b10011 =
0<
b0 ;
b1000 :
b0 9
b10 8
b1000 7
b1000 6
b1000 5
b100 4
b10 3
b1000 2
b1000 1
10
0/
b1000 .
b100000000000000010010011 -
bx ,
0+
b0 *
b100 )
b0 (
b1000 '
b0 &
b0 %
1$
b0 #
0"
0!
$end
#10000
b100000 Q
1!
#20000
0!
#25000
1"
#30000
1/
b0 1
b0 :
b0 B
b0 7
b10 (
b10 @
b10 #
b10 A
00
1$
b0 2
b0 6
b1100 L
b1101111 =
b1100 .
b1100 F
b110000000000000011101111 -
b110000000000000011101111 E
b110000000000000011101111 G
b10000 4
b10000 I
b10000 '
b1000 )
b100 *
b100 H
b100 J
1!
#40000
0!
#50000
b1000 7
b1000 2
b1000 6
b1000 %
b1000 D
b1000 O
0/
b10000 1
b10000 :
b10000 B
b1000 &
b1000 9
b1000 P
b10 ?
b0 (
b0 @
b0 #
b0 A
1$
b11 M
b1 L
b1 K
b110011 =
b0 .
b0 F
b100001000000110110011 -
b100001000000110110011 E
b100001000000110110011 G
b10000 5
b10000 N
b10100 4
b10100 I
b10000 '
b10100 )
b10000 *
b10000 H
b10000 J
1!
#60000
0!
#70000
b1000 1
b1000 :
b1000 B
b0 7
b11000 5
b11000 N
b0 2
b0 6
b0 %
b0 D
b0 O
b11 (
b11 @
b10 #
b10 A
10
b0 ?
1$
b1 M
b0 L
b1100111 =
b1000000011100111 -
b1000000011100111 E
b1000000011100111 G
b1000 4
b1000 I
b10100 '
b11000 )
b10100 *
b10100 H
b10100 J
1!
#80000
0!
#90000
b101 7
b0 (
b0 @
b0 #
b0 A
10
1$
b101 2
b101 6
b1100 4
b1100 I
b101 1
b101 :
b101 B
b10 M
b101 L
b0 K
b10011 =
b101 .
b101 F
b0 &
b0 9
b0 P
b10100000000000100010011 -
b10100000000000100010011 E
b10100000000000100010011 G
b101 5
b101 N
b1101 '
b1100 )
b1000 *
b1000 H
b1000 J
1!
#100000
0!
#110000
b0 5
b0 N
1/
b0 1
b0 :
b0 B
b0 7
b0 2
b0 6
b0 M
b0 L
b0 .
b0 F
b10011 -
b10011 E
b10011 G
b10000 4
b10000 I
b1100 '
b10000 )
b1100 *
b1100 H
b1100 J
1!
#120000
0!
#130000
b110000 5
b110000 N
b11000 7
0/
b110000 1
b110000 :
b110000 B
b11000 2
b11000 6
b11000 %
b11000 D
b11000 O
b11000 &
b11000 9
b11000 P
b10 ?
00
1$
b11 M
b1 L
b1 K
b110011 =
b100001000000110110011 -
b100001000000110110011 E
b100001000000110110011 G
b10100 4
b10100 I
b10000 '
b10100 )
b10000 *
b10000 H
b10000 J
1!
